benderclient/__init__.py
benderclient/benderclient.py
benderclient/utils.py
bender_client-0.4.0.dist-info/LICENCE.txt
bender_client-0.4.0.dist-info/METADATA
bender_client-0.4.0.dist-info/WHEEL
bender_client-0.4.0.dist-info/top_level.txt
bender_client-0.4.0.dist-info/RECORD
