Metadata-Version: 2.1
Name: bender-client
Version: 0.4.0
Summary: Bender Python Client
Home-page: https://bender.dreem.com
Author: Dreem
Author-email: valentin@dreem.com
License: UNKNOWN
Platform: UNKNOWN
Requires-Dist: requests (==2.20.1)
Requires-Dist: python-jose (==3.0.1)
